{"name":"Slow Cooker Buffalo Chicken","description":"Slow Cooker Buffalo Chicken is tender, juicy, tangy, and rich all at the same time! Perfect for sandwiches, nachos, salads, pizza, and more.","ingredients":["2 Tbsp buttermilk powder","1/2 tsp dried parsley","1/4 tsp dried dill","1/4 tsp onion powder","1/8 tsp garlic powder","1/4 tsp lemon pepper","1/8 tsp sugar","1/8 tsp salt","1/8 tsp freshly cracked black pepper","12 oz. hot sauce","2 lbs. boneless, skinless chicken breasts","4 Tbsp butter"],"instructions":"Combine the ranch seasoning (buttermilk powder, parsley, dill, onion powder, garlic powder, lemon pepper, sugar, salt, and pepper) and hot sauce in a bowl. Place the chicken breasts in the bottom of a 3 quart or larger slow cooker. Cut the butter into chunks and place the butter on top of the chicken. Pour the hot sauce mixture over the chicken and butter.  Place the lid on the slow cooker and cook on low heat for four hours. After four hours, use two forks to shred the chicken (if it's not tender enough to shred yet, let it cook a little longer).  Serve the shredded chicken and sauce on sandwiches, in quesadillas, on top of nachos or salads, or as a dip for crackers and chips. ","tags":[],"time":{"prep":"10 minutes mins","cook":"4 hours hrs","active":"","inactive":"","ready":"","total":"4 hours hrs 10 minutes mins"},"servings":"8","image":"https://www.budgetbytes.com/wp-content/uploads/2021/10/Slow-Cooker-Buffalo-Chicken-close.jpg"}